numpyi/__init__.py
numpyi/ci1.py
numpyi/ci2.py
numpyi/ci3.py
numpyi/ci4.py
numpyi/ci5.py
numpyi/dc1.py
numpyi/dc2.py
numpyi/dc3.py
numpyi/dc4.py
numpyi/dc5.py
numpyi-0.11.dist-info/METADATA
numpyi-0.11.dist-info/WHEEL
numpyi-0.11.dist-info/top_level.txt
numpyi-0.11.dist-info/RECORD
