Metadata-Version: 2.4
Name: numpyi
Version: 0.11
Summary: DLcodex
Author: BabaTunde2
Classifier: Programming Language :: Python :: 3
Dynamic: author
Dynamic: classifier
Dynamic: description
Dynamic: description-content-type
Dynamic: summary
